notion_scheduler/__init__.py
notion_scheduler/main.py
notion_scheduler-1.0.3.dist-info/LICENSE
notion_scheduler-1.0.3.dist-info/METADATA
notion_scheduler-1.0.3.dist-info/WHEEL
notion_scheduler-1.0.3.dist-info/entry_points.txt
notion_scheduler-1.0.3.dist-info/top_level.txt
notion_scheduler-1.0.3.dist-info/RECORD
