Metadata-Version: 2.1
Name: notion-scheduler
Version: 1.0.3
Summary: Allows the creation of recurring tasks in Notion.
Home-page: https://github.com/kontheocharis/notion_scheduler
Author: Constantine Theocharis
Author-email: cthe@mailbox.org
License: UNKNOWN
Platform: UNKNOWN
Classifier: Programming Language :: Python :: 3.8
Classifier: Programming Language :: Python :: 3.7
Classifier: License :: OSI Approved :: MIT License
Classifier: Operating System :: Unix
Requires-Python: >=3.7
Requires-Dist: beautifulsoup4 (==4.9.1)
Requires-Dist: bs4 (==0.0.1)
Requires-Dist: cached-property (==1.5.1)
Requires-Dist: certifi (==2020.6.20)
Requires-Dist: chardet (==3.0.4)
Requires-Dist: commonmark (==0.9.1)
Requires-Dist: dictdiffer (==0.8.1)
Requires-Dist: dominate (==2.5.2)
Requires-Dist: durations (==0.3.3)
Requires-Dist: idna (==2.10)
Requires-Dist: mistletoe (==0.7.2)
Requires-Dist: notion-py (==0.0.4)
Requires-Dist: parsedatetime (==2.6)
Requires-Dist: python-dateutil (==2.8.1)
Requires-Dist: python-slugify (==4.0.1)
Requires-Dist: pytz (==2020.1)
Requires-Dist: PyYAML (==5.3.1)
Requires-Dist: recurrent (==0.4.0)
Requires-Dist: requests (==2.24.0)
Requires-Dist: six (==1.15.0)
Requires-Dist: soupsieve (==2.0.1)
Requires-Dist: text-unidecode (==1.3)
Requires-Dist: tzlocal (==2.1)
Requires-Dist: urllib3 (==1.25.10)
